Naver_Api/Api.py
Naver_Api/__init__.py
pynaver_api-0.1.dist-info/METADATA
pynaver_api-0.1.dist-info/WHEEL
pynaver_api-0.1.dist-info/top_level.txt
pynaver_api-0.1.dist-info/RECORD
