Metadata-Version: 2.1
Name: pynaver-api
Version: 0.1
Summary: Naver Api Module
Home-page: https://github.com/AOStormDev/Naver_Api_Module
Author: DevStorm
Author-email: storm@stormdev.club
License: MIT
Platform: UNKNOWN
Classifier: Programming Language :: Python :: 3
Classifier: License :: OSI Approved :: MIT License
Classifier: Operating System :: OS Independent
